devolearn/__init__.py
devolearn/embryo_generator_model/__init__.py
devolearn/embryo_generator_model/embryo_generator_model.py
devolearn/embryo_segmentor/__init__.py
devolearn/embryo_segmentor/embryo_segmentor.py
devolearn/lineage_population_model/__init__.py
devolearn/lineage_population_model/lineage_population_model.py
devolearn/lineage_population_model/scaler/scaler.gz
devolearn/tests/__init__.py
devolearn/tests/test.py
devolearn/tests/sample_data/images/embryo_sample.png
devolearn/tests/sample_data/images/seg_sample.jpg
devolearn/tests/sample_data/videos/embryo_timelapse.mov
devolearn/tests/sample_data/videos/seg_sample.mov
devolearn-0.3.0.dist-info/LICENSE
devolearn-0.3.0.dist-info/METADATA
devolearn-0.3.0.dist-info/WHEEL
devolearn-0.3.0.dist-info/top_level.txt
devolearn-0.3.0.dist-info/RECORD
