Metadata-Version: 2.1
Name: devolearn
Version: 0.3.0
Summary: Accelerate data driven research in developmental biology with deep learning models
Home-page: https://github.com/DevoLearn/devolearn
Author: Mayukh Deb, Ujjwal Singh, Bradly Alicea
Author-email: mayukhmainak2000@gmail.com, ujjwal18113@iiitd.ac.in, balicea@openworm.org
License: UNKNOWN
Platform: UNKNOWN
Classifier: Programming Language :: Python :: 3
Classifier: License :: OSI Approved :: MIT License
Classifier: Operating System :: OS Independent
Requires-Python: >=3.6
Requires-Dist: cycler (==0.10.0)
Requires-Dist: decorator (==4.4.2)
Requires-Dist: efficientnet-pytorch (==0.6.3)
Requires-Dist: future (==0.18.2)
Requires-Dist: imageio (==2.9.0)
Requires-Dist: imgaug (==0.2.5)
Requires-Dist: imutils (==0.5.3)
Requires-Dist: joblib (==1.0.0)
Requires-Dist: kiwisolver (==1.3.1)
Requires-Dist: matplotlib
Requires-Dist: munch (==2.5.0)
Requires-Dist: networkx (==2.5)
Requires-Dist: numpy (==1.19.5)
Requires-Dist: opencv-python (==4.5.1.48)
Requires-Dist: pandas (==1.1.5)
Requires-Dist: Pillow
Requires-Dist: pretrainedmodels (==0.7.4)
Requires-Dist: pyparsing (==2.4.7)
Requires-Dist: python-dateutil (==2.8.1)
Requires-Dist: pytz
Requires-Dist: PyWavelets (==1.1.1)
Requires-Dist: scikit-image
Requires-Dist: scikit-learn (==0.24.0)
Requires-Dist: scipy (==1.5.4)
Requires-Dist: segmentation-models-pytorch (==0.1.3)
Requires-Dist: six (==1.15.0)
Requires-Dist: sklearn (==0.0)
Requires-Dist: threadpoolctl (==2.1.0)
Requires-Dist: tifffile
Requires-Dist: timm (==0.3.2)
Requires-Dist: torch (==1.7.0)
Requires-Dist: torchvision (==0.8.1)
Requires-Dist: tqdm (==4.56.0)
Requires-Dist: typing-extensions (==3.7.4.3)
Requires-Dist: wget (==3.2)
